SampleApp/SampleApp.py
SampleApp/__init__.py
Texternet/__init__.py
Texternet/SampleApp/SampleApp.py
Texternet/SampleApp/__init__.py
Texternet/Uploader/__init__.py
texternet-1.0.4.dist-info/LICENSE
texternet-1.0.4.dist-info/METADATA
texternet-1.0.4.dist-info/WHEEL
texternet-1.0.4.dist-info/top_level.txt
texternet-1.0.4.dist-info/RECORD
