Metadata-Version: 2.1
Name: texternet
Version: 1.0.4
Summary: Package for interacting with and developing apps for Texternet.
Home-page: https://github.com/SonicHedghog/Texternet
Author: Kyle Henry
Author-email: kylehenry@texternet.com
License: UNKNOWN
Platform: UNKNOWN
Classifier: Programming Language :: Python :: 3
Classifier: License :: OSI Approved :: MIT License
Classifier: Operating System :: OS Independent
Requires-Dist: twilio
